MANIFEST.in
README.rst
setup.py
docs/HISTORY.txt
docs/LICENSE.GPL
docs/LICENSE.txt
eea/__init__.py
eea.faceted.inheritance.egg-info/PKG-INFO
eea.faceted.inheritance.egg-info/SOURCES.txt
eea.faceted.inheritance.egg-info/dependency_links.txt
eea.faceted.inheritance.egg-info/entry_points.txt
eea.faceted.inheritance.egg-info/namespace_packages.txt
eea.faceted.inheritance.egg-info/not-zip-safe
eea.faceted.inheritance.egg-info/requires.txt
eea.faceted.inheritance.egg-info/top_level.txt
eea/faceted/__init__.py
eea/faceted/inheritance/README.txt
eea/faceted/inheritance/__init__.py
eea/faceted/inheritance/config.py
eea/faceted/inheritance/configure.zcml
eea/faceted/inheritance/dexterity.zcml
eea/faceted/inheritance/interfaces.py
eea/faceted/inheritance/meta.zcml
eea/faceted/inheritance/minimal.zcml
eea/faceted/inheritance/overrides.zcml
eea/faceted/inheritance/profiles.zcml
eea/faceted/inheritance/setuphandlers.py
eea/faceted/inheritance/version.txt
eea/faceted/inheritance/browser/__init__.py
eea/faceted/inheritance/browser/configure.zcml
eea/faceted/inheritance/browser/app/__init__.py
eea/faceted/inheritance/browser/app/edit.py
eea/faceted/inheritance/browser/javascript/edit.js
eea/faceted/inheritance/browser/templates/edit.pt
eea/faceted/inheritance/criteria/__init__.py
eea/faceted/inheritance/criteria/configure.zcml
eea/faceted/inheritance/criteria/faceted.py
eea/faceted/inheritance/criteria/heritor.py
eea/faceted/inheritance/criteria/interfaces.py
eea/faceted/inheritance/docs/browser.txt
eea/faceted/inheritance/docs/inheritance.txt
eea/faceted/inheritance/exportimport/__init__.py
eea/faceted/inheritance/exportimport/configure.zcml
eea/faceted/inheritance/exportimport/faceted.py
eea/faceted/inheritance/profiles/default/actions.xml
eea/faceted/inheritance/profiles/default/eea.faceted.inheritance.txt
eea/faceted/inheritance/profiles/default/metadata.xml
eea/faceted/inheritance/profiles/uninstall/actions.xml
eea/faceted/inheritance/subtypes/__init__.py
eea/faceted/inheritance/subtypes/configure.zcml
eea/faceted/inheritance/subtypes/interfaces.py
eea/faceted/inheritance/subtypes/subtyper.py
eea/faceted/inheritance/tests/__init__.py
eea/faceted/inheritance/tests/base.py
eea/faceted/inheritance/tests/test_doctests.py
eea/faceted/inheritance/upgrades/__init__.py
eea/faceted/inheritance/upgrades/configure.zcml
eea/faceted/inheritance/versions/__init__.py
