Metadata-Version: 2.1
Name: eea.faceted.inheritance
Version: 6.2
Summary: EEA Faceted Navigation extension that allow a faceted navigable object to inherit faceted configuration from another faceted navigable object.
Home-page: https://github.com/eea/eea.faceted.inheritance
Author: European Environment Agency: IDM2 A-Team
Author-email: eea-edw-a-team-alerts@googlegroups.com
License: GPL
Keywords: EEA Add-ons Plone Zope
Platform: UNKNOWN
Classifier: Framework :: Plone :: 4.3
Classifier: Framework :: Plone :: 5.1
Classifier: Framework :: Plone :: 5.2
Classifier: Framework :: Plone :: Addon
Classifier: Framework :: Zope :: 2
Classifier: Framework :: Zope :: 4
Classifier: Framework :: Zope
Classifier: Programming Language :: Python :: 2.7
Classifier: Programming Language :: Python :: 3.6
Classifier: Programming Language :: Python :: 3.7
Classifier: Programming Language :: Python
Classifier: Topic :: Software Development :: Libraries :: Python Modules
Classifier: License :: OSI Approved :: GNU General Public License (GPL)
Provides-Extra: test
